LICENSE.txt
MANIFEST.in
README.rst
bootstrap.py
pavement.py
paver-minilib.zip
setup.py
cinesync/__init__.py
cinesync/commands.py
cinesync/csc_xml.py
cinesync/event_handler.py
cinesync/frame_annotation.py
cinesync/media_file.py
cinesync/play_range.py
cinesync/session.py
cinesync.egg-info/PKG-INFO
cinesync.egg-info/SOURCES.txt
cinesync.egg-info/dependency_links.txt
cinesync.egg-info/entry_points.txt
cinesync.egg-info/not-zip-safe
cinesync.egg-info/requires.txt
cinesync.egg-info/top_level.txt
docs/conf.py
docs/index.rst
docs/_static/.gitignore
docs/_templates/.gitignore