Metadata-Version: 1.0
Name: cinesync
Version: 1.0
Summary: Library for scripting the cineSync collaborative video review tool
Home-page: http://github.com/jmah/cinesync_python
Author: Jonathon Mah
Author-email: jmah@cinesync.com
License: BSD
Keywords: cinesync
Platform: UNKNOWN
Classifier: Development Status :: 4 - Beta
Classifier: Intended Audience :: Developers
Classifier: License :: OSI Approved :: BSD License
Classifier: Topic :: Multimedia :: Video
